{
  "global_ordering": [
    "p154",
    "p203",
    "p15",
    "p187",
    "p131",
    "p51",
    "p152",
    "p99",
    "p89",
    "p68",
    "p20",
    "p63",
    "p69",
    "p127",
    "p119",
    "p67",
    "p213",
    "p204",
    "p64",
    "p180",
    "p105",
    "p85",
    "p117",
    "p86",
    "p118",
    "p149",
    "p147",
    "p134",
    "p42",
    "p27",
    "p195",
    "p153",
    "p176",
    "p81",
    "p58",
    "p53",
    "p32",
    "p13",
    "p66",
    "p79",
    "p1",
    "p169",
    "p171",
    "p112",
    "p88",
    "p129",
    "p50",
    "p193",
    "p201",
    "p24",
    "p39",
    "p87",
    "p80",
    "p137",
    "p167",
    "p9",
    "p45",
    "p124",
    "p19",
    "p28",
    "p126",
    "p145",
    "p23",
    "p76",
    "p155",
    "p120",
    "p110",
    "p186",
    "p14",
    "p168",
    "p25",
    "p136",
    "p95",
    "p77",
    "p208",
    "p94",
    "p55",
    "p108",
    "p3",
    "p93",
    "p206",
    "p37",
    "p175",
    "p90",
    "p46",
    "p31",
    "p178",
    "p60",
    "p211",
    "p30",
    "p144",
    "p123",
    "p163",
    "p49",
    "p18",
    "p5",
    "p142",
    "p41",
    "p170",
    "p10",
    "p185",
    "p38",
    "p29",
    "p184",
    "p157",
    "p65",
    "p160",
    "p146",
    "p101",
    "p21",
    "p177",
    "p198",
    "p210",
    "p115",
    "p179",
    "p197",
    "p92",
    "p173",
    "p103",
    "p189",
    "p140",
    "p26",
    "p174",
    "p8",
    "p97",
    "p100",
    "p107",
    "p132",
    "p43",
    "p62",
    "p48",
    "p102",
    "p96",
    "p7",
    "p6",
    "p212",
    "p194",
    "p61",
    "p75",
    "p181",
    "p104",
    "p57",
    "p91",
    "p143",
    "p199",
    "p183",
    "p133",
    "p4",
    "p40",
    "p205",
    "p36",
    "p165",
    "p188",
    "p166",
    "p151",
    "p114",
    "p52",
    "p109",
    "p172",
    "p182",
    "p139",
    "p71",
    "p164",
    "p74",
    "p135",
    "p116",
    "p209",
    "p17",
    "p161",
    "p200",
    "p84",
    "p72",
    "p56",
    "p190",
    "p59",
    "p12",
    "p44",
    "p106",
    "p82",
    "p73",
    "p54",
    "p113",
    "p78",
    "p121",
    "p34",
    "p33",
    "p158",
    "p148",
    "p130",
    "p11",
    "p192",
    "p162",
    "p150",
    "p207",
    "p128",
    "p125",
    "p159",
    "p138",
    "p196",
    "p98",
    "p35",
    "p83",
    "p111",
    "p16",
    "p156",
    "p2",
    "p202",
    "p47",
    "p122",
    "p70",
    "p191",
    "p141",
    "p22"
  ],
  "routes": [
    {
      "caregiver_id": "c1",
      "locations": [
        {
          "arrival_time": 44.0,
          "departure_time": 89.0,
          "patient": "p134",
          "service": "s2"
        },
        {
          "arrival_time": 109.0,
          "departure_time": 139.0,
          "patient": "p42",
          "service": "s1"
        },
        {
          "arrival_time": 154.0,
          "departure_time": 184.0,
          "patient": "p27",
          "service": "s1"
        },
        {
          "arrival_time": 204.0,
          "departure_time": 234.0,
          "patient": "p32",
          "service": "s2"
        },
        {
          "arrival_time": 240.0,
          "departure_time": 285.0,
          "patient": "p50",
          "service": "s2"
        },
        {
          "arrival_time": 289.0,
          "departure_time": 304.0,
          "patient": "p14",
          "service": "s1"
        },
        {
          "arrival_time": 313.0,
          "departure_time": 343.0,
          "patient": "p168",
          "service": "s2"
        },
        {
          "arrival_time": 362.0,
          "departure_time": 377.0,
          "patient": "p25",
          "service": "s1"
        },
        {
          "arrival_time": 388.0,
          "departure_time": 433.0,
          "patient": "p136",
          "service": "s2"
        },
        {
          "arrival_time": 446.0,
          "departure_time": 461.0,
          "patient": "p95",
          "service": "s1"
        },
        {
          "arrival_time": 464.0,
          "departure_time": 524.0,
          "patient": "p77",
          "service": "s2"
        },
        {
          "arrival_time": 530.0,
          "departure_time": 575.0,
          "patient": "p46",
          "service": "s1"
        }
      ]
    },
    {
      "caregiver_id": "c2",
      "locations": [
        {
          "arrival_time": 70.0,
          "departure_time": 130.0,
          "patient": "p64",
          "service": "s4"
        },
        {
          "arrival_time": 191.0,
          "departure_time": 206.0,
          "patient": "p147",
          "service": "s4"
        },
        {
          "arrival_time": 220.0,
          "departure_time": 250.0,
          "patient": "p176",
          "service": "s4"
        },
        {
          "arrival_time": 252.0,
          "departure_time": 282.0,
          "patient": "p13",
          "service": "s4"
        },
        {
          "arrival_time": 290.0,
          "departure_time": 335.0,
          "patient": "p193",
          "service": "s4"
        },
        {
          "arrival_time": 338.0,
          "departure_time": 353.0,
          "patient": "p24",
          "service": "s4"
        },
        {
          "arrival_time": 368.0,
          "departure_time": 383.0,
          "patient": "p87",
          "service": "s4"
        },
        {
          "arrival_time": 399.0,
          "departure_time": 414.0,
          "patient": "p80",
          "service": "s4"
        },
        {
          "arrival_time": 424.0,
          "departure_time": 454.0,
          "patient": "p167",
          "service": "s4"
        },
        {
          "arrival_time": 465.0,
          "departure_time": 495.0,
          "patient": "p28",
          "service": "s4"
        }
      ]
    },
    {
      "caregiver_id": "c3",
      "locations": [
        {
          "arrival_time": 210.0,
          "departure_time": 255.0,
          "patient": "p59",
          "service": "s3"
        },
        {
          "arrival_time": 268.0,
          "departure_time": 298.0,
          "patient": "p73",
          "service": "s3"
        },
        {
          "arrival_time": 317.0,
          "departure_time": 347.0,
          "patient": "p121",
          "service": "s3"
        },
        {
          "arrival_time": 356.0,
          "departure_time": 386.0,
          "patient": "p156",
          "service": "s3"
        }
      ]
    },
    {
      "caregiver_id": "c4",
      "locations": [
        {
          "arrival_time": 54.0,
          "departure_time": 69.0,
          "patient": "p119",
          "service": "s4"
        },
        {
          "arrival_time": 108.0,
          "departure_time": 123.0,
          "patient": "p213",
          "service": "s3"
        },
        {
          "arrival_time": 154.0,
          "departure_time": 184.0,
          "patient": "p27",
          "service": "s4"
        },
        {
          "arrival_time": 204.0,
          "departure_time": 234.0,
          "patient": "p32",
          "service": "s4"
        },
        {
          "arrival_time": 270.0,
          "departure_time": 330.0,
          "patient": "p50",
          "service": "s3"
        },
        {
          "arrival_time": 362.0,
          "departure_time": 377.0,
          "patient": "p25",
          "service": "s3"
        },
        {
          "arrival_time": 388.0,
          "departure_time": 433.0,
          "patient": "p136",
          "service": "s4"
        },
        {
          "arrival_time": 444.0,
          "departure_time": 489.0,
          "patient": "p77",
          "service": "s3"
        },
        {
          "arrival_time": 495.0,
          "departure_time": 510.0,
          "patient": "p46",
          "service": "s4"
        },
        {
          "arrival_time": 561.0,
          "departure_time": 591.0,
          "patient": "p6",
          "service": "s4"
        }
      ]
    },
    {
      "caregiver_id": "c5",
      "locations": [
        {
          "arrival_time": 158.0,
          "departure_time": 203.0,
          "patient": "p41",
          "service": "s1"
        },
        {
          "arrival_time": 233.0,
          "departure_time": 248.0,
          "patient": "p170",
          "service": "s1"
        },
        {
          "arrival_time": 262.0,
          "departure_time": 292.0,
          "patient": "p10",
          "service": "s1"
        },
        {
          "arrival_time": 342.0,
          "departure_time": 402.0,
          "patient": "p157",
          "service": "s1"
        },
        {
          "arrival_time": 426.0,
          "departure_time": 456.0,
          "patient": "p114",
          "service": "s1"
        },
        {
          "arrival_time": 464.0,
          "departure_time": 479.0,
          "patient": "p109",
          "service": "s1"
        },
        {
          "arrival_time": 491.0,
          "departure_time": 506.0,
          "patient": "p172",
          "service": "s1"
        },
        {
          "arrival_time": 527.0,
          "departure_time": 542.0,
          "patient": "p182",
          "service": "s2"
        },
        {
          "arrival_time": 552.0,
          "departure_time": 597.0,
          "patient": "p130",
          "service": "s1"
        }
      ]
    },
    {
      "caregiver_id": "c6",
      "locations": [
        {
          "arrival_time": 67.0,
          "departure_time": 97.0,
          "patient": "p67",
          "service": "s4"
        },
        {
          "arrival_time": 108.0,
          "departure_time": 153.0,
          "patient": "p213",
          "service": "s4"
        },
        {
          "arrival_time": 178.0,
          "departure_time": 208.0,
          "patient": "p204",
          "service": "s4"
        },
        {
          "arrival_time": 268.0,
          "departure_time": 313.0,
          "patient": "p117",
          "service": "s4"
        },
        {
          "arrival_time": 464.0,
          "departure_time": 479.0,
          "patient": "p142",
          "service": "s4"
        },
        {
          "arrival_time": 516.0,
          "departure_time": 546.0,
          "patient": "p70",
          "service": "s4"
        }
      ]
    },
    {
      "caregiver_id": "c7",
      "locations": [
        {
          "arrival_time": 83.0,
          "departure_time": 113.0,
          "patient": "p203",
          "service": "s4"
        },
        {
          "arrival_time": 121.0,
          "departure_time": 136.0,
          "patient": "p86",
          "service": "s3"
        },
        {
          "arrival_time": 165.0,
          "departure_time": 195.0,
          "patient": "p19",
          "service": "s4"
        },
        {
          "arrival_time": 198.0,
          "departure_time": 228.0,
          "patient": "p175",
          "service": "s4"
        },
        {
          "arrival_time": 229.0,
          "departure_time": 259.0,
          "patient": "p90",
          "service": "s3"
        },
        {
          "arrival_time": 261.0,
          "departure_time": 306.0,
          "patient": "p211",
          "service": "s3"
        },
        {
          "arrival_time": 323.0,
          "departure_time": 338.0,
          "patient": "p30",
          "service": "s3"
        },
        {
          "arrival_time": 352.0,
          "departure_time": 367.0,
          "patient": "p144",
          "service": "s4"
        },
        {
          "arrival_time": 377.0,
          "departure_time": 392.0,
          "patient": "p123",
          "service": "s3"
        },
        {
          "arrival_time": 395.0,
          "departure_time": 440.0,
          "patient": "p163",
          "service": "s3"
        },
        {
          "arrival_time": 449.0,
          "departure_time": 464.0,
          "patient": "p49",
          "service": "s3"
        },
        {
          "arrival_time": 477.0,
          "departure_time": 522.0,
          "patient": "p177",
          "service": "s4"
        },
        {
          "arrival_time": 529.0,
          "departure_time": 574.0,
          "patient": "p162",
          "service": "s3"
        },
        {
          "arrival_time": 582.0,
          "departure_time": 612.0,
          "patient": "p22",
          "service": "s4"
        }
      ]
    },
    {
      "caregiver_id": "c8",
      "locations": [
        {
          "arrival_time": 60.0,
          "departure_time": 75.0,
          "patient": "p115",
          "service": "s4"
        },
        {
          "arrival_time": 122.0,
          "departure_time": 152.0,
          "patient": "p179",
          "service": "s4"
        },
        {
          "arrival_time": 162.0,
          "departure_time": 177.0,
          "patient": "p197",
          "service": "s3"
        },
        {
          "arrival_time": 211.0,
          "departure_time": 241.0,
          "patient": "p173",
          "service": "s4"
        },
        {
          "arrival_time": 269.0,
          "departure_time": 299.0,
          "patient": "p102",
          "service": "s3"
        },
        {
          "arrival_time": 303.0,
          "departure_time": 318.0,
          "patient": "p36",
          "service": "s3"
        },
        {
          "arrival_time": 328.0,
          "departure_time": 373.0,
          "patient": "p188",
          "service": "s4"
        },
        {
          "arrival_time": 374.0,
          "departure_time": 389.0,
          "patient": "p166",
          "service": "s3"
        },
        {
          "arrival_time": 399.0,
          "departure_time": 414.0,
          "patient": "p151",
          "service": "s4"
        },
        {
          "arrival_time": 527.0,
          "departure_time": 542.0,
          "patient": "p182",
          "service": "s4"
        }
      ]
    },
    {
      "caregiver_id": "c9",
      "locations": [
        {
          "arrival_time": 41.0,
          "departure_time": 101.0,
          "patient": "p51",
          "service": "s3"
        },
        {
          "arrival_time": 163.0,
          "departure_time": 178.0,
          "patient": "p88",
          "service": "s3"
        },
        {
          "arrival_time": 188.0,
          "departure_time": 203.0,
          "patient": "p129",
          "service": "s3"
        },
        {
          "arrival_time": 277.0,
          "departure_time": 337.0,
          "patient": "p145",
          "service": "s3"
        },
        {
          "arrival_time": 382.0,
          "departure_time": 427.0,
          "patient": "p23",
          "service": "s3"
        },
        {
          "arrival_time": 474.0,
          "departure_time": 489.0,
          "patient": "p198",
          "service": "s3"
        }
      ]
    },
    {
      "caregiver_id": "c10",
      "locations": [
        {
          "arrival_time": 30.0,
          "departure_time": 45.0,
          "patient": "p180",
          "service": "s3"
        },
        {
          "arrival_time": 47.0,
          "departure_time": 77.0,
          "patient": "p40",
          "service": "s3"
        },
        {
          "arrival_time": 200.0,
          "departure_time": 230.0,
          "patient": "p205",
          "service": "s3"
        },
        {
          "arrival_time": 283.0,
          "departure_time": 313.0,
          "patient": "p165",
          "service": "s3"
        },
        {
          "arrival_time": 324.0,
          "departure_time": 354.0,
          "patient": "p151",
          "service": "s3"
        },
        {
          "arrival_time": 366.0,
          "departure_time": 396.0,
          "patient": "p52",
          "service": "s3"
        },
        {
          "arrival_time": 464.0,
          "departure_time": 479.0,
          "patient": "p109",
          "service": "s3"
        },
        {
          "arrival_time": 491.0,
          "departure_time": 536.0,
          "patient": "p202",
          "service": "s3"
        }
      ]
    },
    {
      "caregiver_id": "c11",
      "locations": [
        {
          "arrival_time": 132.0,
          "departure_time": 162.0,
          "patient": "p1",
          "service": "s2"
        },
        {
          "arrival_time": 175.0,
          "departure_time": 220.0,
          "patient": "p170",
          "service": "s2"
        },
        {
          "arrival_time": 223.0,
          "departure_time": 283.0,
          "patient": "p185",
          "service": "s2"
        },
        {
          "arrival_time": 292.0,
          "departure_time": 322.0,
          "patient": "p38",
          "service": "s2"
        },
        {
          "arrival_time": 355.0,
          "departure_time": 370.0,
          "patient": "p29",
          "service": "s2"
        },
        {
          "arrival_time": 380.0,
          "departure_time": 395.0,
          "patient": "p184",
          "service": "s2"
        },
        {
          "arrival_time": 417.0,
          "departure_time": 447.0,
          "patient": "p157",
          "service": "s2"
        },
        {
          "arrival_time": 522.0,
          "departure_time": 582.0,
          "patient": "p21",
          "service": "s2"
        }
      ]
    },
    {
      "caregiver_id": "c12",
      "locations": [
        {
          "arrival_time": 47.0,
          "departure_time": 62.0,
          "patient": "p154",
          "service": "s2"
        },
        {
          "arrival_time": 83.0,
          "departure_time": 113.0,
          "patient": "p203",
          "service": "s1"
        },
        {
          "arrival_time": 121.0,
          "departure_time": 136.0,
          "patient": "p86",
          "service": "s2"
        },
        {
          "arrival_time": 155.0,
          "departure_time": 170.0,
          "patient": "p153",
          "service": "s1"
        },
        {
          "arrival_time": 204.0,
          "departure_time": 219.0,
          "patient": "p81",
          "service": "s1"
        },
        {
          "arrival_time": 246.0,
          "departure_time": 276.0,
          "patient": "p53",
          "service": "s2"
        },
        {
          "arrival_time": 299.0,
          "departure_time": 329.0,
          "patient": "p66",
          "service": "s2"
        },
        {
          "arrival_time": 347.0,
          "departure_time": 392.0,
          "patient": "p79",
          "service": "s1"
        },
        {
          "arrival_time": 406.0,
          "departure_time": 451.0,
          "patient": "p207",
          "service": "s1"
        },
        {
          "arrival_time": 473.0,
          "departure_time": 518.0,
          "patient": "p128",
          "service": "s1"
        },
        {
          "arrival_time": 536.0,
          "departure_time": 551.0,
          "patient": "p83",
          "service": "s1"
        }
      ]
    },
    {
      "caregiver_id": "c13",
      "locations": [
        {
          "arrival_time": 41.0,
          "departure_time": 101.0,
          "patient": "p51",
          "service": "s2"
        },
        {
          "arrival_time": 120.0,
          "departure_time": 135.0,
          "patient": "p160",
          "service": "s1"
        },
        {
          "arrival_time": 136.0,
          "departure_time": 181.0,
          "patient": "p146",
          "service": "s1"
        },
        {
          "arrival_time": 193.0,
          "departure_time": 208.0,
          "patient": "p62",
          "service": "s1"
        },
        {
          "arrival_time": 220.0,
          "departure_time": 265.0,
          "patient": "p48",
          "service": "s1"
        },
        {
          "arrival_time": 269.0,
          "departure_time": 299.0,
          "patient": "p102",
          "service": "s2"
        },
        {
          "arrival_time": 301.0,
          "departure_time": 316.0,
          "patient": "p181",
          "service": "s2"
        },
        {
          "arrival_time": 332.0,
          "departure_time": 362.0,
          "patient": "p57",
          "service": "s1"
        },
        {
          "arrival_time": 368.0,
          "departure_time": 413.0,
          "patient": "p143",
          "service": "s2"
        },
        {
          "arrival_time": 426.0,
          "departure_time": 486.0,
          "patient": "p199",
          "service": "s2"
        },
        {
          "arrival_time": 508.0,
          "departure_time": 568.0,
          "patient": "p183",
          "service": "s1"
        },
        {
          "arrival_time": 572.0,
          "departure_time": 602.0,
          "patient": "p4",
          "service": "s1"
        }
      ]
    },
    {
      "caregiver_id": "c14",
      "locations": [
        {
          "arrival_time": 38.0,
          "departure_time": 53.0,
          "patient": "p152",
          "service": "s2"
        },
        {
          "arrival_time": 85.0,
          "departure_time": 130.0,
          "patient": "p99",
          "service": "s2"
        },
        {
          "arrival_time": 146.0,
          "departure_time": 206.0,
          "patient": "p68",
          "service": "s2"
        },
        {
          "arrival_time": 221.0,
          "departure_time": 251.0,
          "patient": "p20",
          "service": "s2"
        },
        {
          "arrival_time": 273.0,
          "departure_time": 333.0,
          "patient": "p127",
          "service": "s2"
        },
        {
          "arrival_time": 365.0,
          "departure_time": 410.0,
          "patient": "p126",
          "service": "s2"
        },
        {
          "arrival_time": 424.0,
          "departure_time": 454.0,
          "patient": "p23",
          "service": "s2"
        },
        {
          "arrival_time": 474.0,
          "departure_time": 489.0,
          "patient": "p198",
          "service": "s2"
        },
        {
          "arrival_time": 497.0,
          "departure_time": 542.0,
          "patient": "p106",
          "service": "s2"
        },
        {
          "arrival_time": 548.0,
          "departure_time": 593.0,
          "patient": "p33",
          "service": "s2"
        }
      ]
    },
    {
      "caregiver_id": "c15",
      "locations": [
        {
          "arrival_time": 49.0,
          "departure_time": 79.0,
          "patient": "p69",
          "service": "s4"
        },
        {
          "arrival_time": 80.0,
          "departure_time": 110.0,
          "patient": "p91",
          "service": "s3"
        },
        {
          "arrival_time": 120.0,
          "departure_time": 135.0,
          "patient": "p74",
          "service": "s4"
        },
        {
          "arrival_time": 158.0,
          "departure_time": 188.0,
          "patient": "p135",
          "service": "s4"
        },
        {
          "arrival_time": 192.0,
          "departure_time": 207.0,
          "patient": "p200",
          "service": "s4"
        },
        {
          "arrival_time": 215.0,
          "departure_time": 260.0,
          "patient": "p84",
          "service": "s4"
        },
        {
          "arrival_time": 263.0,
          "departure_time": 278.0,
          "patient": "p72",
          "service": "s3"
        },
        {
          "arrival_time": 297.0,
          "departure_time": 312.0,
          "patient": "p190",
          "service": "s4"
        },
        {
          "arrival_time": 486.0,
          "departure_time": 501.0,
          "patient": "p150",
          "service": "s4"
        },
        {
          "arrival_time": 518.0,
          "departure_time": 563.0,
          "patient": "p191",
          "service": "s4"
        }
      ]
    },
    {
      "caregiver_id": "c16",
      "locations": [
        {
          "arrival_time": 43.0,
          "departure_time": 103.0,
          "patient": "p169",
          "service": "s2"
        },
        {
          "arrival_time": 116.0,
          "departure_time": 146.0,
          "patient": "p171",
          "service": "s1"
        },
        {
          "arrival_time": 163.0,
          "departure_time": 178.0,
          "patient": "p88",
          "service": "s2"
        },
        {
          "arrival_time": 188.0,
          "departure_time": 203.0,
          "patient": "p129",
          "service": "s2"
        },
        {
          "arrival_time": 223.0,
          "departure_time": 238.0,
          "patient": "p210",
          "service": "s2"
        },
        {
          "arrival_time": 250.0,
          "departure_time": 280.0,
          "patient": "p92",
          "service": "s2"
        },
        {
          "arrival_time": 286.0,
          "departure_time": 316.0,
          "patient": "p173",
          "service": "s2"
        },
        {
          "arrival_time": 321.0,
          "departure_time": 336.0,
          "patient": "p174",
          "service": "s1"
        },
        {
          "arrival_time": 364.0,
          "departure_time": 394.0,
          "patient": "p8",
          "service": "s1"
        },
        {
          "arrival_time": 431.0,
          "departure_time": 446.0,
          "patient": "p97",
          "service": "s1"
        },
        {
          "arrival_time": 470.0,
          "departure_time": 485.0,
          "patient": "p100",
          "service": "s2"
        },
        {
          "arrival_time": 493.0,
          "departure_time": 523.0,
          "patient": "p132",
          "service": "s2"
        },
        {
          "arrival_time": 541.0,
          "departure_time": 586.0,
          "patient": "p43",
          "service": "s1"
        }
      ]
    },
    {
      "caregiver_id": "c17",
      "locations": [
        {
          "arrival_time": 76.0,
          "departure_time": 91.0,
          "patient": "p139",
          "service": "s2"
        },
        {
          "arrival_time": 134.0,
          "departure_time": 164.0,
          "patient": "p71",
          "service": "s1"
        },
        {
          "arrival_time": 182.0,
          "departure_time": 197.0,
          "patient": "p164",
          "service": "s1"
        },
        {
          "arrival_time": 203.0,
          "departure_time": 233.0,
          "patient": "p116",
          "service": "s2"
        },
        {
          "arrival_time": 260.0,
          "departure_time": 320.0,
          "patient": "p17",
          "service": "s2"
        },
        {
          "arrival_time": 333.0,
          "departure_time": 378.0,
          "patient": "p161",
          "service": "s2"
        },
        {
          "arrival_time": 390.0,
          "departure_time": 405.0,
          "patient": "p56",
          "service": "s1"
        },
        {
          "arrival_time": 425.0,
          "departure_time": 485.0,
          "patient": "p82",
          "service": "s1"
        },
        {
          "arrival_time": 489.0,
          "departure_time": 504.0,
          "patient": "p113",
          "service": "s1"
        },
        {
          "arrival_time": 507.0,
          "departure_time": 567.0,
          "patient": "p98",
          "service": "s1"
        }
      ]
    },
    {
      "caregiver_id": "c18",
      "locations": [
        {
          "arrival_time": 106.0,
          "departure_time": 136.0,
          "patient": "p76",
          "service": "s4"
        },
        {
          "arrival_time": 154.0,
          "departure_time": 169.0,
          "patient": "p155",
          "service": "s4"
        },
        {
          "arrival_time": 182.0,
          "departure_time": 227.0,
          "patient": "p120",
          "service": "s4"
        },
        {
          "arrival_time": 236.0,
          "departure_time": 281.0,
          "patient": "p110",
          "service": "s4"
        },
        {
          "arrival_time": 287.0,
          "departure_time": 317.0,
          "patient": "p186",
          "service": "s4"
        },
        {
          "arrival_time": 323.0,
          "departure_time": 368.0,
          "patient": "p101",
          "service": "s4"
        },
        {
          "arrival_time": 382.0,
          "departure_time": 427.0,
          "patient": "p122",
          "service": "s4"
        }
      ]
    },
    {
      "caregiver_id": "c19",
      "locations": [
        {
          "arrival_time": 51.0,
          "departure_time": 111.0,
          "patient": "p118",
          "service": "s2"
        },
        {
          "arrival_time": 124.0,
          "departure_time": 169.0,
          "patient": "p149",
          "service": "s1"
        },
        {
          "arrival_time": 191.0,
          "departure_time": 206.0,
          "patient": "p147",
          "service": "s1"
        },
        {
          "arrival_time": 223.0,
          "departure_time": 268.0,
          "patient": "p201",
          "service": "s1"
        },
        {
          "arrival_time": 274.0,
          "departure_time": 289.0,
          "patient": "p24",
          "service": "s1"
        },
        {
          "arrival_time": 291.0,
          "departure_time": 321.0,
          "patient": "p39",
          "service": "s2"
        },
        {
          "arrival_time": 342.0,
          "departure_time": 402.0,
          "patient": "p137",
          "service": "s1"
        },
        {
          "arrival_time": 424.0,
          "departure_time": 454.0,
          "patient": "p167",
          "service": "s1"
        },
        {
          "arrival_time": 465.0,
          "departure_time": 495.0,
          "patient": "p28",
          "service": "s1"
        },
        {
          "arrival_time": 517.0,
          "departure_time": 532.0,
          "patient": "p125",
          "service": "s1"
        },
        {
          "arrival_time": 545.0,
          "departure_time": 575.0,
          "patient": "p47",
          "service": "s2"
        }
      ]
    },
    {
      "caregiver_id": "c20",
      "locations": [
        {
          "arrival_time": 34.0,
          "departure_time": 79.0,
          "patient": "p15",
          "service": "s3"
        },
        {
          "arrival_time": 85.0,
          "departure_time": 130.0,
          "patient": "p187",
          "service": "s4"
        },
        {
          "arrival_time": 151.0,
          "departure_time": 166.0,
          "patient": "p131",
          "service": "s4"
        },
        {
          "arrival_time": 178.0,
          "departure_time": 208.0,
          "patient": "p89",
          "service": "s3"
        },
        {
          "arrival_time": 221.0,
          "departure_time": 251.0,
          "patient": "p20",
          "service": "s4"
        },
        {
          "arrival_time": 273.0,
          "departure_time": 333.0,
          "patient": "p127",
          "service": "s3"
        },
        {
          "arrival_time": 370.0,
          "departure_time": 385.0,
          "patient": "p54",
          "service": "s4"
        },
        {
          "arrival_time": 399.0,
          "departure_time": 459.0,
          "patient": "p148",
          "service": "s4"
        },
        {
          "arrival_time": 478.0,
          "departure_time": 508.0,
          "patient": "p11",
          "service": "s4"
        },
        {
          "arrival_time": 511.0,
          "departure_time": 571.0,
          "patient": "p16",
          "service": "s4"
        }
      ]
    },
    {
      "caregiver_id": "c21",
      "locations": [
        {
          "arrival_time": 65.0,
          "departure_time": 110.0,
          "patient": "p208",
          "service": "s3"
        },
        {
          "arrival_time": 145.0,
          "departure_time": 190.0,
          "patient": "p94",
          "service": "s3"
        },
        {
          "arrival_time": 199.0,
          "departure_time": 229.0,
          "patient": "p55",
          "service": "s3"
        },
        {
          "arrival_time": 268.0,
          "departure_time": 283.0,
          "patient": "p12",
          "service": "s3"
        },
        {
          "arrival_time": 457.0,
          "departure_time": 472.0,
          "patient": "p196",
          "service": "s3"
        },
        {
          "arrival_time": 483.0,
          "departure_time": 543.0,
          "patient": "p111",
          "service": "s3"
        }
      ]
    },
    {
      "caregiver_id": "c22",
      "locations": [
        {
          "arrival_time": 30.0,
          "departure_time": 45.0,
          "patient": "p180",
          "service": "s2"
        },
        {
          "arrival_time": 70.0,
          "departure_time": 115.0,
          "patient": "p105",
          "service": "s1"
        },
        {
          "arrival_time": 160.0,
          "departure_time": 205.0,
          "patient": "p85",
          "service": "s1"
        },
        {
          "arrival_time": 268.0,
          "departure_time": 313.0,
          "patient": "p117",
          "service": "s2"
        },
        {
          "arrival_time": 358.0,
          "departure_time": 403.0,
          "patient": "p18",
          "service": "s1"
        },
        {
          "arrival_time": 415.0,
          "departure_time": 460.0,
          "patient": "p5",
          "service": "s1"
        },
        {
          "arrival_time": 464.0,
          "departure_time": 479.0,
          "patient": "p142",
          "service": "s2"
        },
        {
          "arrival_time": 537.0,
          "departure_time": 552.0,
          "patient": "p21",
          "service": "s1"
        },
        {
          "arrival_time": 552.0,
          "departure_time": 597.0,
          "patient": "p141",
          "service": "s1"
        }
      ]
    },
    {
      "caregiver_id": "c23",
      "locations": [
        {
          "arrival_time": 100.0,
          "departure_time": 145.0,
          "patient": "p63",
          "service": "s1"
        },
        {
          "arrival_time": 199.0,
          "departure_time": 229.0,
          "patient": "p55",
          "service": "s1"
        },
        {
          "arrival_time": 238.0,
          "departure_time": 268.0,
          "patient": "p93",
          "service": "s2"
        },
        {
          "arrival_time": 296.0,
          "departure_time": 311.0,
          "patient": "p206",
          "service": "s2"
        },
        {
          "arrival_time": 391.0,
          "departure_time": 436.0,
          "patient": "p37",
          "service": "s1"
        },
        {
          "arrival_time": 440.0,
          "departure_time": 470.0,
          "patient": "p96",
          "service": "s2"
        },
        {
          "arrival_time": 485.0,
          "departure_time": 530.0,
          "patient": "p7",
          "service": "s2"
        },
        {
          "arrival_time": 561.0,
          "departure_time": 591.0,
          "patient": "p6",
          "service": "s2"
        }
      ]
    },
    {
      "caregiver_id": "c24",
      "locations": [
        {
          "arrival_time": 106.0,
          "departure_time": 151.0,
          "patient": "p131",
          "service": "s3"
        },
        {
          "arrival_time": 157.0,
          "departure_time": 172.0,
          "patient": "p149",
          "service": "s4"
        },
        {
          "arrival_time": 178.0,
          "departure_time": 193.0,
          "patient": "p58",
          "service": "s4"
        },
        {
          "arrival_time": 246.0,
          "departure_time": 276.0,
          "patient": "p53",
          "service": "s4"
        },
        {
          "arrival_time": 299.0,
          "departure_time": 329.0,
          "patient": "p66",
          "service": "s3"
        },
        {
          "arrival_time": 347.0,
          "departure_time": 392.0,
          "patient": "p79",
          "service": "s4"
        },
        {
          "arrival_time": 408.0,
          "departure_time": 453.0,
          "patient": "p34",
          "service": "s4"
        },
        {
          "arrival_time": 492.0,
          "departure_time": 522.0,
          "patient": "p192",
          "service": "s4"
        },
        {
          "arrival_time": 560.0,
          "departure_time": 590.0,
          "patient": "p2",
          "service": "s3"
        }
      ]
    },
    {
      "caregiver_id": "c25",
      "locations": [
        {
          "arrival_time": 70.0,
          "departure_time": 130.0,
          "patient": "p64",
          "service": "s1"
        },
        {
          "arrival_time": 269.0,
          "departure_time": 314.0,
          "patient": "p78",
          "service": "s2"
        },
        {
          "arrival_time": 536.0,
          "departure_time": 551.0,
          "patient": "p159",
          "service": "s1"
        }
      ]
    },
    {
      "caregiver_id": "c26",
      "locations": [
        {
          "arrival_time": 133.0,
          "departure_time": 148.0,
          "patient": "p204",
          "service": "s3"
        },
        {
          "arrival_time": 164.0,
          "departure_time": 209.0,
          "patient": "p108",
          "service": "s3"
        },
        {
          "arrival_time": 230.0,
          "departure_time": 260.0,
          "patient": "p3",
          "service": "s3"
        },
        {
          "arrival_time": 296.0,
          "departure_time": 311.0,
          "patient": "p206",
          "service": "s3"
        },
        {
          "arrival_time": 391.0,
          "departure_time": 436.0,
          "patient": "p37",
          "service": "s3"
        },
        {
          "arrival_time": 441.0,
          "departure_time": 471.0,
          "patient": "p133",
          "service": "s3"
        },
        {
          "arrival_time": 572.0,
          "departure_time": 602.0,
          "patient": "p4",
          "service": "s3"
        }
      ]
    },
    {
      "caregiver_id": "c27",
      "locations": [
        {
          "arrival_time": 27.0,
          "departure_time": 42.0,
          "patient": "p65",
          "service": "s3"
        },
        {
          "arrival_time": 136.0,
          "departure_time": 181.0,
          "patient": "p146",
          "service": "s3"
        },
        {
          "arrival_time": 215.0,
          "departure_time": 245.0,
          "patient": "p212",
          "service": "s3"
        },
        {
          "arrival_time": 255.0,
          "departure_time": 285.0,
          "patient": "p194",
          "service": "s3"
        },
        {
          "arrival_time": 295.0,
          "departure_time": 325.0,
          "patient": "p61",
          "service": "s3"
        },
        {
          "arrival_time": 346.0,
          "departure_time": 361.0,
          "patient": "p75",
          "service": "s3"
        },
        {
          "arrival_time": 367.0,
          "departure_time": 427.0,
          "patient": "p104",
          "service": "s3"
        },
        {
          "arrival_time": 432.0,
          "departure_time": 462.0,
          "patient": "p143",
          "service": "s3"
        }
      ]
    },
    {
      "caregiver_id": "c28",
      "locations": [
        {
          "arrival_time": 147.0,
          "departure_time": 177.0,
          "patient": "p1",
          "service": "s1"
        },
        {
          "arrival_time": 180.0,
          "departure_time": 195.0,
          "patient": "p9",
          "service": "s2"
        },
        {
          "arrival_time": 236.0,
          "departure_time": 281.0,
          "patient": "p110",
          "service": "s1"
        },
        {
          "arrival_time": 287.0,
          "departure_time": 317.0,
          "patient": "p186",
          "service": "s2"
        },
        {
          "arrival_time": 323.0,
          "departure_time": 368.0,
          "patient": "p101",
          "service": "s1"
        },
        {
          "arrival_time": 379.0,
          "departure_time": 394.0,
          "patient": "p44",
          "service": "s1"
        },
        {
          "arrival_time": 414.0,
          "departure_time": 429.0,
          "patient": "p158",
          "service": "s1"
        },
        {
          "arrival_time": 472.0,
          "departure_time": 532.0,
          "patient": "p35",
          "service": "s1"
        }
      ]
    },
    {
      "caregiver_id": "c29",
      "locations": [
        {
          "arrival_time": 100.0,
          "departure_time": 145.0,
          "patient": "p63",
          "service": "s4"
        },
        {
          "arrival_time": 164.0,
          "departure_time": 194.0,
          "patient": "p195",
          "service": "s4"
        },
        {
          "arrival_time": 196.0,
          "departure_time": 211.0,
          "patient": "p112",
          "service": "s3"
        },
        {
          "arrival_time": 225.0,
          "departure_time": 255.0,
          "patient": "p103",
          "service": "s3"
        },
        {
          "arrival_time": 257.0,
          "departure_time": 287.0,
          "patient": "p189",
          "service": "s4"
        },
        {
          "arrival_time": 322.0,
          "departure_time": 337.0,
          "patient": "p140",
          "service": "s3"
        },
        {
          "arrival_time": 348.0,
          "departure_time": 378.0,
          "patient": "p26",
          "service": "s3"
        },
        {
          "arrival_time": 470.0,
          "departure_time": 485.0,
          "patient": "p100",
          "service": "s3"
        },
        {
          "arrival_time": 503.0,
          "departure_time": 518.0,
          "patient": "p107",
          "service": "s4"
        },
        {
          "arrival_time": 571.0,
          "departure_time": 601.0,
          "patient": "p43",
          "service": "s4"
        }
      ]
    },
    {
      "caregiver_id": "c30",
      "locations": [
        {
          "arrival_time": 60.0,
          "departure_time": 75.0,
          "patient": "p45",
          "service": "s1"
        },
        {
          "arrival_time": 108.0,
          "departure_time": 153.0,
          "patient": "p124",
          "service": "s2"
        },
        {
          "arrival_time": 165.0,
          "departure_time": 195.0,
          "patient": "p19",
          "service": "s1"
        },
        {
          "arrival_time": 229.0,
          "departure_time": 259.0,
          "patient": "p90",
          "service": "s2"
        },
        {
          "arrival_time": 264.0,
          "departure_time": 279.0,
          "patient": "p31",
          "service": "s2"
        },
        {
          "arrival_time": 287.0,
          "departure_time": 302.0,
          "patient": "p178",
          "service": "s2"
        },
        {
          "arrival_time": 305.0,
          "departure_time": 320.0,
          "patient": "p60",
          "service": "s1"
        },
        {
          "arrival_time": 323.0,
          "departure_time": 338.0,
          "patient": "p30",
          "service": "s2"
        },
        {
          "arrival_time": 352.0,
          "departure_time": 367.0,
          "patient": "p144",
          "service": "s2"
        },
        {
          "arrival_time": 395.0,
          "departure_time": 440.0,
          "patient": "p163",
          "service": "s2"
        },
        {
          "arrival_time": 449.0,
          "departure_time": 464.0,
          "patient": "p49",
          "service": "s1"
        },
        {
          "arrival_time": 477.0,
          "departure_time": 522.0,
          "patient": "p177",
          "service": "s2"
        },
        {
          "arrival_time": 531.0,
          "departure_time": 576.0,
          "patient": "p209",
          "service": "s1"
        },
        {
          "arrival_time": 579.0,
          "departure_time": 609.0,
          "patient": "p138",
          "service": "s1"
        }
      ]
    }
  ]
}